chess_python/__init__.py
chess_python/chess.py
chess_python/game.py
chess_python/utils.py
chess_python_pip-0.1.12.dist-info/WHEEL
chess_python_pip-0.1.12.dist-info/METADATA
chess_python_pip-0.1.12.dist-info/RECORD
