Metadata-Version: 2.1
Name: chess-python-pip
Version: 0.1.12
Summary: Python implementation of the game of chess.
Author: pacanada
Author-email: pereirapcanada@gmail.com
Requires-Python: >=3.8,<4.0
Classifier: Programming Language :: Python :: 3
Classifier: Programming Language :: Python :: 3.8
Classifier: Programming Language :: Python :: 3.9
Classifier: Programming Language :: Python :: 3.10
Classifier: Programming Language :: Python :: 3.11
